fresh_orm/__init__.py
fresh_orm/config.py
fresh_orm/model.py
fresh_orm/repository.py
fresh_orm-0.0.2.dist-info/LICENSE
fresh_orm-0.0.2.dist-info/METADATA
fresh_orm-0.0.2.dist-info/WHEEL
fresh_orm-0.0.2.dist-info/top_level.txt
fresh_orm-0.0.2.dist-info/RECORD
