Metadata-Version: 2.1
Name: fresh_orm
Version: 0.0.2
Summary: A lightweight SQLite Object-Relational Mapping (ORM) library for Python, designed to simplify database interactions and provide an intuitive interface for managing SQLite tables and relationships.
Home-page: https://github.com/roymanigley/fresh_orm
Author: Roy Manigley
Author-email: roy.manigley@gmail.com
License: MIT
Classifier: Development Status :: 5 - Production/Stable
Classifier: Intended Audience :: Developers
Classifier: License :: OSI Approved :: MIT License
Classifier: Operating System :: POSIX :: Linux
Classifier: Programming Language :: Python :: 3.11
License-File: LICENSE
